{"parts":[{"id":1,"partNumber":"?","dimensions":{"x":130,"y":25,"z":810},"orientation":{"allowedDown":["front","bottom","right","back"],"preferredDown":"right"},"weight":0.0,"layoutHint":{"surfaceId":0,"rotation":0.0,"weightFactor":0.0},"minMargin":0.0},{"id":2,"partNumber":"?","dimensions":{"x":291,"y":810,"z":394},"orientation":{"allowedDown":["left","bottom","right","back"]},"weight":0.0,"layoutHint":{"origin":{"x":405,"y":310,"z":145},"surfaceId":0,"rotation":90.0,"weightFactor":5.0,"orientation":"left"},"minMargin":0.0},{"id":3,"partNumber":"?","dimensions":{"x":187,"y":42,"z":77},"orientation":{"allowedDown":["front","bottom","right","back"],"preferredDown":"right"},"weight":0.0,"layoutHint":{"surfaceId":0,"rotation":0.0,"weightFactor":0.0},"minMargin":0.0},{"id":2,"partNumber":"?","dimensions":{"x":463,"y":393,"z":77},"orientation":{"allowedDown":["top","front","bottom","right","back"],"preferredDown":"front"},"weight":0.0,"layoutHint":{"surfaceId":0,"rotation":0.0,"weightFactor":0.0},"minMargin":0.0},{"id":1,"partNumber":"?","dimensions":{"x":505,"y":244,"z":40},"orientation":{"allowedDown":["front","bottom","right"],"preferredDown":"front"},"weight":0.0,"layoutHint":{"origin":{"x":183,"y":252,"z":122},"surfaceId":1,"rotation":90.0,"weightFactor":10.0,"orientation":"front"},"minMargin":0.0},{"id":1,"partNumber":"?","dimensions":{"x":321,"y":810,"z":22},"orientation":{"allowedDown":["top","front","bottom","right"],"preferredDown":"right"},"weight":0.0,"layoutHint":{"origin":{"x":405,"y":79,"z":160},"surfaceId":0,"rotation":90.0,"weightFactor":1.0,"orientation":"right"},"minMargin":0.0},{"id":1,"partNumber":"?","dimensions":{"x":595,"y":109,"z":263},"orientation":{"allowedDown":["top","left","front","bottom","back"]},"weight":0.0,"layoutHint":{"surfaceId":0,"rotation":0.0,"weightFactor":0.0},"minMargin":0.0},{"id":2,"partNumber":"?","dimensions":{"x":810,"y":23,"z":237},"orientation":{"allowedDown":["bottom","right","back"]},"weight":0.0,"layoutHint":{"origin":{"x":405,"y":101,"z":118},"surfaceId":0,"rotation":0.0,"weightFactor":8.0,"orientation":"bottom"},"minMargin":0.0},{"id":2,"partNumber":"?","dimensions":{"x":186,"y":431,"z":350},"orientation":{"allowedDown":["top","bottom","right"]},"weight":0.0,"layoutHint":{"origin":{"x":378,"y":598,"z":175},"surfaceId":1,"rotation":90.0,"weightFactor":9.0,"orientation":"bottom"},"minMargin":0.0},{"id":1,"partNumber":"?","dimensions":{"x":163,"y":227,"z":96},"orientation":{"allowedDown":["top","front","bottom","back"],"preferredDown":"back"},"weight":0.0,"layoutHint":{"surfaceId":0,"rotation":0.0,"weightFactor":0.0},"minMargin":0.0},{"id":0,"partNumber":"?","dimensions":{"x":54,"y":595,"z":487},"orientation":{"allowedDown":["top","left","front","bottom","back"],"preferredDown":"bottom"},"weight":0.0,"layoutHint":{"surfaceId":0,"rotation":0.0,"weightFactor":0.0},"minMargin":0.0},{"id":1,"partNumber":"?","dimensions":{"x":21,"y":379,"z":459},"orientation":{"allowedDown":["top","left","bottom","back"],"preferredDown":"bottom"},"weight":0.0,"layoutHint":{"origin":{"x":189,"y":32,"z":229},"surfaceId":0,"rotation":90.0,"weightFactor":10.0,"orientation":"bottom"},"minMargin":0.0},{"id":2,"partNumber":"?","dimensions":{"x":80,"y":43,"z":94},"orientation":{"allowedDown":["top","left","front","bottom","right"],"preferredDown":"bottom"},"weight":0.0,"layoutHint":{"origin":{"x":770,"y":21,"z":47},"surfaceId":0,"rotation":0.0,"weightFactor":10.0,"orientation":"bottom"},"minMargin":0.0},{"id":2,"partNumber":"?","dimensions":{"x":351,"y":21,"z":185},"orientation":{"allowedDown":["top","left","front","bottom","right","back"]},"weight":0.0,"layoutHint":{"surfaceId":0,"rotation":0.0,"weightFactor":0.0},"minMargin":0.0},{"id":1,"partNumber":"?","dimensions":{"x":22,"y":392,"z":351},"orientation":{"allowedDown":["left","front","bottom","right","back"],"preferredDown":"front"},"weight":0.0,"layoutHint":{"origin":{"x":554,"y":11,"z":196},"surfaceId":0,"rotation":90.0,"weightFactor":2.0,"orientation":"front"},"minMargin":0.0},{"id":3,"partNumber":"?","dimensions":{"x":314,"y":219,"z":505},"orientation":{"allowedDown":["top","front","bottom","right","back"]},"weight":0.0,"layoutHint":{"surfaceId":0,"rotation":0.0,"weightFactor":0.0},"minMargin":0.0},{"id":0,"partNumber":"?","dimensions":{"x":198,"y":22,"z":379},"orientation":{"allowedDown":["front","left","bottom","back"],"preferredDown":"left"},"weight":0.0,"layoutHint":{"surfaceId":0,"rotation":0.0,"weightFactor":0.0},"minMargin":0.0}],"wagonHint":{"wagon":{"wagonId":"wagon","capabilities":[],"surfaces":[{"id":0,"dimensions":{"x":830,"y":811,"z":500},"origin":{"x":0,"y":0,"z":0}},{"id":1,"dimensions":{"x":830,"y":811,"z":500},"origin":{"x":0,"y":0,"z":500}}],"dimensions":{"x":830,"y":811,"z":500}},"weightFactor":10.0}}