{"parts":[{"id":2,"partNumber":"?","dimensions":{"x":257,"y":549,"z":284},"orientation":{"allowedDown":["top","front","bottom","right","back"]},"weight":0.0,"layoutHint":{"surfaceId":0,"rotation":0.0,"weightFactor":0.0},"minMargin":0.0},{"id":2,"partNumber":"?","dimensions":{"x":23,"y":169,"z":218},"orientation":{"allowedDown":["left","front","bottom","back"],"preferredDown":"front"},"weight":0.0,"layoutHint":{"surfaceId":0,"rotation":0.0,"weightFactor":0.0},"minMargin":0.0},{"id":1,"partNumber":"?","dimensions":{"x":42,"y":312,"z":218},"orientation":{"allowedDown":["top","front","left","bottom","back"],"preferredDown":"front"},"weight":0.0,"layoutHint":{"surfaceId":0,"rotation":0.0,"weightFactor":0.0},"minMargin":0.0},{"id":2,"partNumber":"?","dimensions":{"x":20,"y":1065,"z":115},"orientation":{"allowedDown":["front","bottom","right","back"]},"weight":0.0,"layoutHint":{"origin":{"x":532,"y":165,"z":10},"surfaceId":1,"rotation":90.0,"weightFactor":3.0,"orientation":"right"},"minMargin":0.0},{"id":3,"partNumber":"?","dimensions":{"x":661,"y":165,"z":497},"orientation":{"allowedDown":["top","front","bottom","right","back"],"preferredDown":"front"},"weight":0.0,"layoutHint":{"origin":{"x":587,"y":738,"z":82},"surfaceId":0,"rotation":0.0,"weightFactor":10.0,"orientation":"front"},"minMargin":0.0},{"id":3,"partNumber":"?","dimensions":{"x":371,"y":345,"z":117},"orientation":{"allowedDown":["left","front","bottom","right","back"]},"weight":0.0,"layoutHint":{"surfaceId":0,"rotation":0.0,"weightFactor":0.0},"minMargin":0.0},{"id":2,"partNumber":"?","dimensions":{"x":290,"y":117,"z":495},"orientation":{"allowedDown":["top","left","bottom","right","back"]},"weight":0.0,"layoutHint":{"origin":{"x":402,"y":431,"z":247},"surfaceId":0,"rotation":0.0,"weightFactor":5.0,"orientation":"top"},"minMargin":0.0},{"id":0,"partNumber":"?","dimensions":{"x":81,"y":1065,"z":113},"orientation":{"allowedDown":["top","front","left","bottom","back"],"preferredDown":"bottom"},"weight":0.0,"layoutHint":{"surfaceId":0,"rotation":0.0,"weightFactor":0.0},"minMargin":0.0},{"id":2,"partNumber":"?","dimensions":{"x":119,"y":210,"z":1065},"orientation":{"allowedDown":["top","front","left","bottom","back"],"preferredDown":"back"},"weight":0.0,"layoutHint":{"origin":{"x":532,"y":393,"z":105},"surfaceId":1,"rotation":90.0,"weightFactor":6.0,"orientation":"back"},"minMargin":0.0},{"id":2,"partNumber":"?","dimensions":{"x":1065,"y":301,"z":353},"orientation":{"allowedDown":["top","front","left","bottom","right","back"]},"weight":0.0,"layoutHint":{"origin":{"x":532,"y":700,"z":176},"surfaceId":1,"rotation":0.0,"weightFactor":4.0,"orientation":"bottom"},"minMargin":0.0},{"id":1,"partNumber":"?","dimensions":{"x":407,"y":1065,"z":20},"orientation":{"allowedDown":["top","left","front","bottom"],"preferredDown":"left"},"weight":0.0,"layoutHint":{"surfaceId":0,"rotation":0.0,"weightFactor":0.0},"minMargin":0.0},{"id":1,"partNumber":"?","dimensions":{"x":27,"y":1065,"z":45},"orientation":{"allowedDown":["top","front","bottom"]},"weight":0.0,"layoutHint":{"origin":{"x":532,"y":94,"z":22},"surfaceId":1,"rotation":90.0,"weightFactor":10.0,"orientation":"bottom"},"minMargin":0.0},{"id":0,"partNumber":"?","dimensions":{"x":264,"y":373,"z":380},"orientation":{"allowedDown":["top","left","front","bottom"],"preferredDown":"left"},"weight":0.0,"layoutHint":{"origin":{"x":190,"y":186,"z":132},"surfaceId":0,"rotation":0.0,"weightFactor":5.0,"orientation":"left"},"minMargin":0.0},{"id":2,"partNumber":"?","dimensions":{"x":39,"y":383,"z":65},"orientation":{"allowedDown":["left","bottom","right","back"]},"weight":0.0,"layoutHint":{"surfaceId":0,"rotation":0.0,"weightFactor":0.0},"minMargin":0.0},{"id":2,"partNumber":"?","dimensions":{"x":1065,"y":97,"z":304},"orientation":{"allowedDown":["top","front","left","bottom","back"]},"weight":0.0,"layoutHint":{"surfaceId":0,"rotation":0.0,"weightFactor":0.0},"minMargin":0.0},{"id":1,"partNumber":"?","dimensions":{"x":538,"y":446,"z":373},"orientation":{"allowedDown":["left","front","bottom","back"]},"weight":0.0,"layoutHint":{"origin":{"x":649,"y":186,"z":223},"surfaceId":0,"rotation":0.0,"weightFactor":5.0,"orientation":"front"},"minMargin":0.0},{"id":3,"partNumber":"?","dimensions":{"x":1065,"y":357,"z":91},"orientation":{"allowedDown":["left","front","bottom"]},"weight":0.0,"layoutHint":{"origin":{"x":532,"y":268,"z":178},"surfaceId":1,"rotation":0.0,"weightFactor":6.0,"orientation":"front"},"minMargin":0.0}],"wagonHint":{"wagon":{"wagonId":"wagon","capabilities":[],"surfaces":[{"id":0,"dimensions":{"x":1199,"y":1010,"z":500},"origin":{"x":0,"y":0,"z":0}},{"id":1,"dimensions":{"x":1199,"y":1010,"z":500},"origin":{"x":0,"y":0,"z":500}}],"dimensions":{"x":1199,"y":1010,"z":500}},"weightFactor":10.0}}